Flask_J2S/__init__.py
Flask_J2S/core.py
Flask_J2S/core_driver.py
Flask_J2S/core_generate.py
Flask_J2S/core_server.py
Flask_J2S-2.0.dist-info/LICENSE
Flask_J2S-2.0.dist-info/METADATA
Flask_J2S-2.0.dist-info/WHEEL
Flask_J2S-2.0.dist-info/top_level.txt
Flask_J2S-2.0.dist-info/RECORD
