Metadata-Version: 2.1
Name: Flask_J2S
Version: 2.0
Summary: Set Flask From JSON
Home-page: https://github.com/staykimin/Flask-J2S
Author: KIMIN
Author-email: staykimin@gmail.com
License: MIT
Project-URL: Documentation, https://github.com/staykimin/Flask-J2S
Project-URL: Funding, https://github.com/staykimin/Flask-J2S
Project-URL: Say Thanks!, https://saweria.co/staykimin
Project-URL: Source, https://github.com/staykimin/Flask-J2S
Project-URL: Tracker, https://github.com/staykimin/Flask-J2S/issues
Keywords: Kimin,Flask,Flask-J2S,J2S
Classifier: Development Status :: 3 - Alpha
Classifier: Intended Audience :: Developers
Classifier: Topic :: Utilities
Classifier: License :: OSI Approved :: MIT License
Classifier: Programming Language :: Python :: 3
Classifier: Programming Language :: Python :: 3.7
Classifier: Programming Language :: Python :: 3.8
Classifier: Programming Language :: Python :: 3.9
Classifier: Programming Language :: Python :: 3.10
License-File: LICENSE
Requires-Dist: Flask
Requires-Dist: Flask-Cors
Requires-Dist: colorama
Requires-Dist: requests
Requires-Dist: Modul-Wrapper
